controllers/__init__.py
controllers/main/__init__.py
controllers/main/device_controller.py
controllers/main/project_controller.py
controllers/main/sms_record_controller.py
controllers/main/sms_report_controller.py
controllers/sub/__init__.py
controllers/sub/device_controller.py
controllers/sub/group_controller.py
controllers/sub/sms_controller.py
core/__init__.py
core/command_handler.py
core/core.py
core/settings.py
utils/__init__.py
utils/constants.py
utils/formatters.py
utils/helpers.py
smsctl-1.0.7.dist-info/METADATA
smsctl-1.0.7.dist-info/WHEEL
smsctl-1.0.7.dist-info/entry_points.txt
smsctl-1.0.7.dist-info/top_level.txt
smsctl-1.0.7.dist-info/RECORD
